odoo/addons/product_expiry_simple/README.rst
odoo/addons/product_expiry_simple/__init__.py
odoo/addons/product_expiry_simple/__manifest__.py
odoo/addons/product_expiry_simple/data/product_removal.xml
odoo/addons/product_expiry_simple/i18n/de.po
odoo/addons/product_expiry_simple/i18n/es.po
odoo/addons/product_expiry_simple/i18n/fi.po
odoo/addons/product_expiry_simple/i18n/fr.po
odoo/addons/product_expiry_simple/i18n/it.po
odoo/addons/product_expiry_simple/i18n/nl_NL.po
odoo/addons/product_expiry_simple/i18n/product_expiry_simple.pot
odoo/addons/product_expiry_simple/i18n/sl.po
odoo/addons/product_expiry_simple/models/__init__.py
odoo/addons/product_expiry_simple/models/product_template.py
odoo/addons/product_expiry_simple/models/stock_lot.py
odoo/addons/product_expiry_simple/models/stock_move.py
odoo/addons/product_expiry_simple/models/stock_move_line.py
odoo/addons/product_expiry_simple/models/stock_picking.py
odoo/addons/product_expiry_simple/models/stock_quant.py
odoo/addons/product_expiry_simple/readme/CONTRIBUTORS.rst
odoo/addons/product_expiry_simple/readme/DESCRIPTION.rst
odoo/addons/product_expiry_simple/static/description/icon.png
odoo/addons/product_expiry_simple/static/description/index.html
odoo/addons/product_expiry_simple/views/product_template.xml
odoo/addons/product_expiry_simple/views/stock_lot.xml
odoo/addons/product_expiry_simple/views/stock_move.xml
odoo/addons/product_expiry_simple/views/stock_move_line.xml
odoo/addons/product_expiry_simple/views/stock_picking.xml
odoo/addons/product_expiry_simple/views/stock_quant.xml
odoo/addons/product_expiry_simple/wizards/__init__.py
odoo/addons/product_expiry_simple/wizards/stock_assign_serial.py
odoo/addons/product_expiry_simple/wizards/stock_assign_serial_view.xml
odoo_addon_product_expiry_simple-16.0.1.2.0.4.dist-info/METADATA
odoo_addon_product_expiry_simple-16.0.1.2.0.4.dist-info/WHEEL
odoo_addon_product_expiry_simple-16.0.1.2.0.4.dist-info/top_level.txt
odoo_addon_product_expiry_simple-16.0.1.2.0.4.dist-info/RECORD
